Workbook

Sheet Sheet3
A3: Row Labels | B3: Sum of Total Sales | C3: Sum of Profit
A4: North | B4: 1377334.4 | C4: 235977.59
A5: West | B5: 1310189 | C5: 232075.55
A6: South | B6: 803471.74 | C6: 130423.02
A7: East | B7: 803057.52 | C7: 130715.75
A8: Grand Total | B8: 4294052.6 | C8: 729191.91

Sheet Sheet4
A3: Row Labels | B3: Sum of Total Sales | C3: Sum of Profit
A4: Laptop | B4: 1877688.5 | C4: 348805.07
A5: Monitor | B5: 695340.95 | C5: 104138.99
A6: Printer | B6: 457859.24 | C6: 66839.325
A7: SSD 1TB | B7: 418392.9 | C7: 70989.717
A8: Office Chair | B8: 331036.17 | C8: 48382.36
A9: Webcam | B9: 148202 | C9: 26540.21
A10: Router | B10: 134705.27 | C10: 24711.454
A11: Keyboard | B11: 110550.06 | C11: 18304.123
A12: Headset | B12: 63822.601 | C12: 11428.394
A13: Mouse | B13: 56454.96 | C13: 9052.2619
A14: Grand Total | B14: 4294052.6 | C14: 729191.91

Sheet Sheet5
A3: Row Labels | B3: Sum of Total Sales | C3: Sum of Profit
A4: Electronics | B4: 2721231.4 | C4: 479484.28
A5: Office Equipment | B5: 457859.24 | C5: 66839.325
A6: Storage | B6: 418392.9 | C6: 70989.717
A7: Furniture | B7: 331036.17 | C7: 48382.36
A8: Accessories | B8: 230827.62 | C8: 38784.779
A9: Networking | B9: 134705.27 | C9: 24711.454
A10: Grand Total | B10: 4294052.6 | C10: 729191.91

Sheet Dashboard
A1: BUSINESS SALES & PROFIT ANALYTICS DASHBOARD
D3: Total Sales | E3: Total profit | F3: Profit Margin | G3: Total Orders
D4: 4294052.6 | E4: 729191.91 | F4: 0.1698 | G4: 100
A6: Sales & Profit by Region | F6: Sales & Profit by Product | I6: Category
B19: Sales & Profit by Product

Sheet Raw_Data
A1: Order ID | B1: Order Date | C1: Product | D1: Category | E1: Region | F1: Salesperson | G1: Quantity | H1: Unit Price | I1: Discount | J1: Total Sales | K1: Profit | L1: Payment Mode
A2: ORD0001 | B2: 27-02-2026 | C2: Monitor | D2: Electronics | E2: North | F2: Neha | G2: 1 | H2: 18695.67 | I2: 0.02 | J2: =G2*H2*(1-I2) -> 18321.757 | K2: =J2-(G2*H2*0.78) -> 3739.134 | L2: Bank Transfer
A3: ORD0002 | B3: 10-05-2026 | C3: Laptop | D3: Electronics | E3: South | F3: Karan | G3: 1 | H3: 51424.52 | I3: 0.02 | J3: =G3*H3*(1-I3) -> 50396.03 | K3: =J3-(G3*H3*0.78) -> 10284.904 | L3: Credit Card
A4: ORD0003 | B4: 14-07-2026 | C4: SSD 1TB | D4: Storage | E4: West | F4: Ananya | G4: 5 | H4: 6821.81 | I4: 0 | J4: =G4*H4*(1-I4) -> 34109.05 | K4: =J4-(G4*H4*0.78) -> 7503.991 | L4: Debit Card
A5: ORD0004 | B5: 27-01-2026 | C5: Keyboard | D5: Accessories | E5: North | F5: Ananya | G5: 4 | H5: 1931.68 | I5: 0.05 | J5: =G5*H5*(1-I5) -> 7340.384 | K5: =J5-(G5*H5*0.78) -> 1313.5424 | L5: Debit Card
A6: ORD0005 | B6: 28-04-2026 | C6: Office Chair | D6: Furniture | E6: West | F6: Neha | G6: 5 | H6: 8917.69 | I6: 0.15 | J6: =G6*H6*(1-I6) -> 37900.183 | K6: =J6-(G6*H6*0.78) -> 3121.1915 | L6: Debit Card
A7: ORD0006 | B7: 18-01-2026 | C7: Office Chair | D7: Furniture | E7: South | F7: Vikram | G7: 6 | H7: 8605.2 | I7: 0.15 | J7: =G7*H7*(1-I7) -> 43886.52 | K7: =J7-(G7*H7*0.78) -> 3614.184 | L7: UPI
A8: ORD0007 | B8: 12-06-2026 | C8: Mouse | D8: Accessories | E8: South | F8: Ananya | G8: 2 | H8: 882.74 | I8: 0.08 | J8: =G8*H8*(1-I8) -> 1624.2416 | K8: =J8-(G8*H8*0.78) -> 247.1672 | L8: Debit Card
A9: ORD0008 | B9: 15-06-2026 | C9: Mouse | D9: Accessories | E9: South | F9: Priya | G9: 5 | H9: 929.06 | I9: 0.15 | J9: =G9*H9*(1-I9) -> 3948.505 | K9: =J9-(G9*H9*0.78) -> 325.171 | L9: Credit Card
A10: ORD0009 | B10: 26-06-2026 | C10: SSD 1TB | D10: Storage | E10: East | F10: Aarav | G10: 7 | H10: 6260.75 | I10: 0.15 | J10: =G10*H10*(1-I10) -> 37251.463 | K10: =J10-(G10*H10*0.78) -> 3067.7675 | L10: Credit Card
A11: ORD0010 | B11: 24-02-2026 | C11: Laptop | D11: Electronics | E11: East | F11: Priya | G11: 6 | H11: 54130.25 | I11: 0 | J11: =G11*H11*(1-I11) -> 324781.5 | K11: =J11-(G11*H11*0.78) -> 71451.93 | L11: Bank Transfer
A12: ORD0011 | B12: 05-03-2026 | C12: Router | D12: Networking | E12: East | F12: Karan | G12: 8 | H12: 3300.01 | I12: 0.02 | J12: =G12*H12*(1-I12) -> 25872.078 | K12: =J12-(G12*H12*0.78) -> 5280.016 | L12: Bank Transfer
A13: ORD0012 | B13: 11-05-2026 | C13: Printer | D13: Office Equipment | E13: North | F13: Neha | G13: 4 | H13: 13494.65 | I13: 0.02 | J13: =G13*H13*(1-I13) -> 52899.028 | K13: =J13-(G13*H13*0.78) -> 10795.72 | L13: Credit Card
... A101: ORD0100 | B101: 18-02-2026 | C101: Mouse | D101: Accessories | E101: South | F101: Neha | G101: 8 | H101: 907.38 | I101: 0.08 | J101: =G101*H101*(1-I101) -> 6678.3168 | K101: =J101-(G101*H101*0.78) -> 1016.2656 | L101: Debit Card
J102: =SUM(Table1[Total Sales]) -> 4294052.6 | K102: =SUM(Table1[Profit]) -> 729191.91

Sheet Analysis
A1: KPI | B1: Value
A2: total sales | B2: =SUM(Raw_Data!J2:J101) -> 4294052.6
A3: total profit | B3: =SUM(Raw_Data!K2:K101) -> 729191.91
A4: profit margin | B4: =B3/B2 -> 0.16981439
A7: Region | B7: total sales | C7: total profit
A8: north | B8: =SUMIF(Raw_Data!E:E,A8,Raw_Data!J:J) -> 1377334.4 | C8: =SUMIF(Raw_Data!E:E,A8,Raw_Data!K:K) -> 235977.59
A9: south | B9: =SUMIF(Raw_Data!E:E,A9,Raw_Data!J:J) -> 803471.74 | C9: =SUMIF(Raw_Data!E:E,A9,Raw_Data!K:K) -> 130423.02
A10: east | B10: =SUMIF(Raw_Data!E:E,A10,Raw_Data!J:J) -> 803057.52 | C10: =SUMIF(Raw_Data!E:E,A10,Raw_Data!K:K) -> 130715.75
A11: west | B11: =SUMIF(Raw_Data!E:E,A11,Raw_Data!J:J) -> 1310189 | C11: =SUMIF(Raw_Data!E:E,A11,Raw_Data!K:K) -> 232075.55
A13: Row Labels | B13: Sum of Total Sales | C13: Sum of Profit | E13: Row Labels | F13: Sum of Total Sales | G13: Sum of Profit
A14: Electronics | B14: 2721231.4 | C14: 479484.28 | E14: Laptop | F14: 1877688.5 | G14: 348805.07
A15: Office Equipment | B15: 457859.24 | C15: 66839.325 | E15: Monitor | F15: 695340.95 | G15: 104138.99
A16: Storage | B16: 418392.9 | C16: 70989.717 | E16: Printer | F16: 457859.24 | G16: 66839.325
A17: Furniture | B17: 331036.17 | C17: 48382.36 | E17: SSD 1TB | F17: 418392.9 | G17: 70989.717
A18: Accessories | B18: 230827.62 | C18: 38784.779 | E18: Office Chair | F18: 331036.17 | G18: 48382.36
A19: Networking | B19: 134705.27 | C19: 24711.454 | E19: Webcam | F19: 148202 | G19: 26540.21
A20: Grand Total | B20: 4294052.6 | C20: 729191.91 | E20: Router | F20: 134705.27 | G20: 24711.454
E21: Keyboard | F21: 110550.06 | G21: 18304.123
E22: Headset | F22: 63822.601 | G22: 11428.394
A23: Row Labels | B23: Sum of Total Sales | C23: Sum of Profit | E23: Mouse | F23: 56454.96 | G23: 9052.2619
A24: North | B24: 1377334.4 | C24: 235977.59 | E24: Grand Total | F24: 4294052.6 | G24: 729191.91
A25: West | B25: 1310189 | C25: 232075.55
A26: South | B26: 803471.74 | C26: 130423.02
A27: East | B27: 803057.52 | C27: 130715.75
A28: Grand Total | B28: 4294052.6 | C28: 729191.91
